LICENSE
MANIFEST.in
README.rst
pyproject.toml
setup.py
depends/install_pfft.sh
pfft/__init__.py
pfft/core.c
pfft/core.pyx
pfft/libmpi.pxd
pfft/version.py
pfft/tests/__init__.py
pfft/tests/test_pfft.py
pfft_python.egg-info/PKG-INFO
pfft_python.egg-info/SOURCES.txt
pfft_python.egg-info/dependency_links.txt
pfft_python.egg-info/not-zip-safe
pfft_python.egg-info/requires.txt
pfft_python.egg-info/top_level.txt
scripts/pfft-roundtrip-matrix.py