Metadata-Version: 2.4
Name: pfft-python
Version: 0.1.23
Summary: python binding of PFFT, a massively parallel FFT library
Home-page: http://github.com/rainwoodman/pfft-python
Author: Yu Feng
Author-email: rainwoodman@gmail.com
License: GPL3
Requires: numpy
License-File: LICENSE
Requires-Dist: cython
Requires-Dist: numpy
Requires-Dist: mpi4py
Dynamic: author
Dynamic: author-email
Dynamic: home-page
Dynamic: license
Dynamic: license-file
Dynamic: requires
Dynamic: requires-dist
Dynamic: summary
